config/__init__.py
config/settings.py
config/urls.py
config/wsgi.py
django_liked-1.0.2.dist-info/DESCRIPTION.rst
django_liked-1.0.2.dist-info/METADATA
django_liked-1.0.2.dist-info/RECORD
django_liked-1.0.2.dist-info/WHEEL
django_liked-1.0.2.dist-info/metadata.json
django_liked-1.0.2.dist-info/pbr.json
django_liked-1.0.2.dist-info/top_level.txt
liked/__init__.py
liked/admin.py
liked/app.py
liked/apps.py
liked/models.py
liked/tests.py
liked/views.py
liked/migrations/0001_initial.py
liked/migrations/__init__.py
