Metadata-Version: 2.0
Name: django-liked
Version: 1.0.2
Summary: A django likes app
Home-page: https://github.com/amyth/django-liked
Author: Amyth Arora
Author-email: mail@amythsingh.com
License: MIT License
Platform: UNKNOWN
